CHANGELOG.md
LICENSE
MANIFEST.in
README.rst
setup.cfg
setup.py
pycloudflare/__init__.py
pycloudflare/config.py
pycloudflare/exceptions.py
pycloudflare/models.py
pycloudflare/services.py
pycloudflare/utils.py
pycloudflare.egg-info/PKG-INFO
pycloudflare.egg-info/SOURCES.txt
pycloudflare.egg-info/dependency_links.txt
pycloudflare.egg-info/requires.txt
pycloudflare.egg-info/top_level.txt
tests/__init__.py
tests/fakes.py
tests/test_integration.py
tests/test_services.py
tests/models/__init__.py
tests/models/test_page_rule.py
tests/models/test_record.py
tests/models/test_user.py
tests/models/test_zone.py
tests/models/test_zone_settings.py