Metadata-Version: 1.1
Name: pycloudflare
Version: 2.2.0
Summary: Python client for CloudFlare.
Home-page: https://github.com/yola/pycloudflare
Author: Yola
Author-email: engineers@yola.com
License: MIT (Expat)
Platform: UNKNOWN
Classifier: License :: OSI Approved :: MIT License
Classifier: Programming Language :: Python :: 2.7
Classifier: Programming Language :: Python :: 3
